{"month":"11","num":348,"link":"","year":"2007","news":"","safe_title":"Close to You","transcript":"Man: \u003c\u003cSinging\u003e\u003e Why do birds suddenly appear\nMan: \u003c\u003cSinging\u003e\u003e Every tiiiime you are neeear\nMan: Wait, are those turkey vultures?\nMan: Okay, listen, are you a zombie?\nWoman: Hurrghhh...\n{{We should probably talk about this before the wedding.}}","alt":"We should probably talk about this before the wedding.","img":"https://imgs.xkcd.com/comics/close_to_you.png","title":"Close to You","day":"23"}
